bytedance_nodus/__init__.py
bytedance_nodus-0.0.1.dist-info/METADATA
bytedance_nodus-0.0.1.dist-info/WHEEL
bytedance_nodus-0.0.1.dist-info/top_level.txt
bytedance_nodus-0.0.1.dist-info/RECORD
